{"data": [{"id": "1d36742e3f24f50e4e7ae82801ee92c1", "number": "5155197100", "date": "2021-01-23 13:08:00", "subject": "3", "recorded-or-robo": "Y", "city": "", "state": "IA", "area-code": "515"}, {"id": "3decc6bfadaa436a105714c6ba583adf", "number": "3303562423", "date": "2020-01-23 13:42:00", "subject": "3", "recorded-or-robo": "Y", "city": "", "state": "OH", "area-code": "216"}, {"id": "1d36742e3f24f50e4e7ae82801ee8817", "number": "3303562423", "date": "2020-01-23 13:42:00", "subject": "3", "recorded-or-robo": "Y", "city": "", "state": "OH", "area-code": "216"}, {"id": "3decc6bfadaa436a105714c6ba172441", "number": "8302000746", "date": "2021-01-11 08:00:00", "subject": "2", "recorded-or-robo": "Y", "city": "NEW BRAUNFELS", "state": "TX", "area-code": "830"}, {"id": "1d36742e3f24f50e4e7ae82801ae7063", "number": "8302000746", "date": "2021-01-11 08:00:00", "subject": "2", "recorded-or-robo": "Y", "city": "NEW BRAUNFELS", "state": "TX", "area-code": "830"}, {"id": "3decc6bfadaa436a105714c6ba171562", "number": "8448943951", "date": "2021-01-23 00:00:00", "subject": "3", "recorded-or-robo": "Y", "city": "", "state": "CO", "area-code": "303"}, {"id": "1d36742e3f24f50e4e7ae82801ae6a7d", "number": "8448943951", "date": "2021-01-23 00:00:00", "subject": "3", "recorded-or-robo": "Y", "city": "", "state": "CO", "area-code": "303"}, {"id": "3decc6bfadaa436a105714c6ba17037c", "number": "8166780778", "date": "2021-01-23 11:18:00", "subject": "3", "recorded-or-robo": "N", "city": "", "state": "WV", "area-code": "304"}, {"id": "1d36742e3f24f50e4e7ae82801ae2f63", "number": "8166780778", "date": "2021-01-23 11:18:00", "subject": "3", "recorded-or-robo": "N", "city": "", "state": "WV", "area-code": "304"}, {"id": "3decc6bfadaa436a105714c6ba17136a", "number": "", "date": "2021-01-23 10:20:00", "subject": "3", "recorded-or-robo": "Y", "city": "", "state": "OK", "area-code": "405"}, {"id": "1d36742e3f24f50e4e7ae82801ae5d70", "number": "", "date": "2021-01-23 10:20:00", "subject": "3", "recorded-or-robo": "Y", "city": "", "state": "OK", "area-code": "405"}, {"id": "3decc6bfadaa436a105714c6ba170899", "number": "6367345904", "date": "2021-01-22 11:42:00", "subject": "2", "recorded-or-robo": "Y", "city": "WARRENTON", "state": "MO", "area-code": "636"}, {"id": "1d36742e3f24f50e4e7ae82801ae4d9f", "number": "6367345904", "date": "2021-01-22 11:42:00", "subject": "2", "recorded-or-robo": "Y", "city": "WARRENTON", "state": "MO", "area-code": "636"}, {"id": "3decc6bfadaa436a105714c6ba1706b3", "number": "9403021710", "date": "2021-01-23 12:23:00", "subject": "1", "recorded-or-robo": "Y", "city": "Gulfport", "state": "MS", "area-code": "228"}, {"id": "1d36742e3f24f50e4e7ae82801ae3e06", "number": "9403021710", "date": "2021-01-23 12:23:00", "subject": "1", "recorded-or-robo": "Y", "city": "Gulfport", "state": "MS", "area-code": "228"}, {"id": "3decc6bfadaa436a105714c6ba568120", "number": "2178344086", "date": "2021-01-23 14:12:34", "subject": "3", "recorded-or-robo": "N", "city": "", "state": "FL", "area-code": "813"}, {"id": "1d36742e3f24f50e4e7ae82801ecdd73", "number": "2178344086", "date": "2021-01-23 14:12:34", "subject": "3", "recorded-or-robo": "N", "city": "", "state": "FL", "area-code": "813"}, {"id": "3decc6bfadaa436a105714c6ba16f76e", "number": "5312244113", "date": "2021-01-22 14:41:00", "subject": "0", "recorded-or-robo": "N", "city": "", "state": "TX", "area-code": "210"}, {"id": "3decc6bfadaa436a105714c6ba16ee90", "number": "8002491948", "date": "2021-01-23 14:00:00", "subject": "0", "recorded-or-robo": "Y", "city": "", "state": "NJ", "area-code": "856"}, {"id": "1d36742e3f24f50e4e7ae82801ae274a", "number": "5312244113", "date": "2021-01-22 14:41:00", "subject": "0", "recorded-or-robo": "N", "city": "", "state": "TX", "area-code": "210"}, {"id": "1d36742e3f24f50e4e7ae82801ae263f", "number": "8002491948", "date": "2021-01-23 14:00:00", "subject": "0", "recorded-or-robo": "Y", "city": "", "state": "NJ", "area-code": "856"}, {"id": "3decc6bfadaa436a105714c6ba16e6bd", "number": "2189612012", "date": "2021-01-22 00:00:00", "subject": "2", "recorded-or-robo": "N", "city": "Independence", "state": "OH", "area-code": "440"}, {"id": "1d36742e3f24f50e4e7ae82801ae24ac", "number": "2189612012", "date": "2021-01-22 00:00:00", "subject": "2", "recorded-or-robo": "N", "city": "Independence", "state": "OH", "area-code": "440"}, {"id": "3decc6bfadaa436a105714c6ba16da17", "number": "2202032013", "date": "2021-01-18 15:30:00", "subject": "2", "recorded-or-robo": "", "city": "Bremen", "state": "AL", "area-code": "256"}, {"id": "1d36742e3f24f50e4e7ae82801ae2249", "number": "2202032013", "date": "2021-01-18 15:30:00", "subject": "2", "recorded-or-robo": "", "city": "Bremen", "state": "AL", "area-code": "256"}, {"id": "3decc6bfadaa436a105714c6ba16d8d1", "number": "4076413143", "date": "2021-01-23 13:00:00", "subject": "2", "recorded-or-robo": "Y", "city": "Exeter", "state": "NH", "area-code": "603"}, {"id": "1d36742e3f24f50e4e7ae82801ae1e62", "number": "4076413143", "date": "2021-01-23 13:00:00", "subject": "2", "recorded-or-robo": "Y", "city": "Exeter", "state": "NH", "area-code": "603"}, {"id": "3decc6bfadaa436a105714c6ba16d7a5", "number": "7342350719", "date": "2021-01-23 12:47:00", "subject": "0", "recorded-or-robo": "Y", "city": "", "state": "IL", "area-code": "847"}, {"id": "1d36742e3f24f50e4e7ae82801ae0f09", "number": "7342350719", "date": "2021-01-23 12:47:00", "subject": "0", "recorded-or-robo": "Y", "city": "", "state": "IL", "area-code": "847"}, {"id": "3decc6bfadaa436a105714c6ba16cdf4", "number": "8339303044", "date": "2021-01-23 13:35:00", "subject": "11", "recorded-or-robo": "Y", "city": "", "state": "VA", "area-code": "757"}, {"id": "1d36742e3f24f50e4e7ae82801ae039c", "number": "8339303044", "date": "2021-01-23 13:35:00", "subject": "11", "recorded-or-robo": "Y", "city": "", "state": "VA", "area-code": "757"}, {"id": "3decc6bfadaa436a105714c6ba16c3cc", "number": "3262225027", "date": "2021-01-22 16:03:00", "subject": "2", "recorded-or-robo": "N", "city": "Columbus", "state": "OH", "area-code": "614"}, {"id": "1d36742e3f24f50e4e7ae82801ae0371", "number": "3262225027", "date": "2021-01-22 16:03:00", "subject": "2", "recorded-or-robo": "N", "city": "Columbus", "state": "OH", "area-code": "614"}, {"id": "3decc6bfadaa436a105714c6ba16b8c3", "number": "8327318148", "date": "2021-01-23 08:13:00", "subject": "2", "recorded-or-robo": "Y", "city": "Pinole", "state": "CA", "area-code": "510"}, {"id": "3decc6bfadaa436a105714c6ba16b595", "number": "9712678385", "date": "2021-01-07 09:54:00", "subject": "3", "recorded-or-robo": "", "city": "BISHOP", "state": "CA", "area-code": "971"}, {"id": "1d36742e3f24f50e4e7ae82801adf6d1", "number": "8327318148", "date": "2021-01-23 08:13:00", "subject": "2", "recorded-or-robo": "Y", "city": "Pinole", "state": "CA", "area-code": "510"}, {"id": "1d36742e3f24f50e4e7ae82801adeb91", "number": "9712678385", "date": "2021-01-07 09:54:00", "subject": "3", "recorded-or-robo": "", "city": "BISHOP", "state": "CA", "area-code": "971"}, {"id": "3decc6bfadaa436a105714c6ba16a82e", "number": "2282544166", "date": "2021-01-23 13:00:00", "subject": "0", "recorded-or-robo": "Y", "city": "", "state": "GA", "area-code": "228"}, {"id": "1d36742e3f24f50e4e7ae82801ade66a", "number": "2282544166", "date": "2021-01-23 13:00:00", "subject": "0", "recorded-or-robo": "Y", "city": "", "state": "GA", "area-code": "228"}, {"id": "3decc6bfadaa436a105714c6ba16a7bd", "number": "6463780795", "date": "2021-01-23 12:45:00", "subject": "2", "recorded-or-robo": "Y", "city": "Chicago", "state": "IL", "area-code": "773"}, {"id": "1d36742e3f24f50e4e7ae82801add8e3", "number": "6463780795", "date": "2021-01-23 12:45:00", "subject": "2", "recorded-or-robo": "Y", "city": "Chicago", "state": "IL", "area-code": "773"}, {"id": "3decc6bfadaa436a105714c6ba169c45", "number": "4256289450", "date": "2021-01-22 09:19:00", "subject": "4", "recorded-or-robo": "Y", "city": "Bellevue", "state": "WA", "area-code": "425"}, {"id": "1d36742e3f24f50e4e7ae82801add1fb", "number": "4256289450", "date": "2021-01-22 09:19:00", "subject": "4", "recorded-or-robo": "Y", "city": "Bellevue", "state": "WA", "area-code": "425"}, {"id": "3decc6bfadaa436a105714c6ba168edc", "number": "4085749246", "date": "2021-01-23 11:47:00", "subject": "2", "recorded-or-robo": "Y", "city": "Knoxville", "state": "TN", "area-code": "865"}, {"id": "1d36742e3f24f50e4e7ae82801adcb0d", "number": "4085749246", "date": "2021-01-23 11:47:00", "subject": "2", "recorded-or-robo": "Y", "city": "Knoxville", "state": "TN", "area-code": "865"}, {"id": "3decc6bfadaa436a105714c6ba1681e8", "number": "3152328257", "date": "2021-01-22 14:53:00", "subject": "1", "recorded-or-robo": "Y", "city": "Chesterfield", "state": "MO", "area-code": "636"}, {"id": "3decc6bfadaa436a105714c6ba167b54", "number": "2186491564", "date": "2021-01-22 00:00:00", "subject": "3", "recorded-or-robo": "N", "city": "Independence", "state": "OH", "area-code": "440"}, {"id": "1d36742e3f24f50e4e7ae82801adc571", "number": "3152328257", "date": "2021-01-22 14:53:00", "subject": "1", "recorded-or-robo": "Y", "city": "Chesterfield", "state": "MO", "area-code": "636"}, {"id": "1d36742e3f24f50e4e7ae82801adb57c", "number": "2186491564", "date": "2021-01-22 00:00:00", "subject": "3", "recorded-or-robo": "N", "city": "Independence", "state": "OH", "area-code": "440"}, {"id": "3decc6bfadaa436a105714c6ba167185", "number": "5033828289", "date": "2021-01-08 09:14:00", "subject": "3", "recorded-or-robo": "", "city": "BISHOP", "state": "CA", "area-code": "971"}]}